inspect_model/__init__.py
inspect_model/utils.py
inspect_model/test_settings.py
inspect_model/models.py
inspect_model/tests.py
django_inspect_model-0.7.dist-info/metadata.json
django_inspect_model-0.7.dist-info/METADATA
django_inspect_model-0.7.dist-info/RECORD
django_inspect_model-0.7.dist-info/WHEEL
django_inspect_model-0.7.dist-info/DESCRIPTION.rst
django_inspect_model-0.7.dist-info/top_level.txt
