Metadata-Version: 1.1
Name: django-inspect-model
Version: 0.7
Summary: Model inspection for Django
Home-page: https://github.com/magopian/django-inspect-model
Author: Mathieu agopian
Author-email: mathieu.agopian@gmail.com
License: BSD license, see LICENSE file
Platform: UNKNOWN
Classifier: Development Status :: 3 - Alpha
Classifier: Environment :: Web Environment
Classifier: Framework :: Django
Classifier: Intended Audience :: Developers
Classifier: License :: OSI Approved :: BSD License
Classifier: Natural Language :: English
Classifier: Programming Language :: Python
Classifier: Programming Language :: Python :: 2
Classifier: Programming Language :: Python :: 2.7
Classifier: Programming Language :: Python :: 3
Classifier: Programming Language :: Python :: 3.3
